pytest_ndb/VERSION
pytest_ndb/__init__.py
pytest_ndb-1.0.0.dist-info/LICENSE
pytest_ndb-1.0.0.dist-info/METADATA
pytest_ndb-1.0.0.dist-info/WHEEL
pytest_ndb-1.0.0.dist-info/top_level.txt
pytest_ndb-1.0.0.dist-info/RECORD
