Metadata-Version: 2.1
Name: pytest-ndb
Version: 1.0.0
Summary: pytest notebook debugger
Author-email: Richard Shadrach <rhshadrach@gmail.com>
License: BSD-3-Clause
Project-URL: homepage, https://github.com/rhshadrach/pytest-ndb
Project-URL: documentation, https://github.com/rhshadrach/pytest-ndb
Project-URL: repository, https://github.com/rhshadrach/pytest-ndb
Project-URL: issues, https://github.com/rhshadrach/pytest-ndb/issues
Classifier: Programming Language :: Python :: 3
Requires-Python: >=3.8
License-File: LICENSE
Requires-Dist: pytest
Provides-Extra: dev
Requires-Dist: pytest-ndb[doc,lint,test] ; extra == 'dev'
Provides-Extra: doc
Requires-Dist: sphinx ; extra == 'doc'
Provides-Extra: lint
Requires-Dist: black ; extra == 'lint'
Requires-Dist: codespell ; extra == 'lint'
Requires-Dist: flake8 ; extra == 'lint'
Requires-Dist: isort ; extra == 'lint'
Requires-Dist: mypy ; extra == 'lint'
Requires-Dist: pylint ; extra == 'lint'
Requires-Dist: pyright ; extra == 'lint'
Requires-Dist: pyupgrade ; extra == 'lint'
Requires-Dist: ruff ; extra == 'lint'
Requires-Dist: vulture ; extra == 'lint'
Provides-Extra: test
Requires-Dist: pytest ; extra == 'test'
